ppt_json/__init__.py
ppt_json/json_resource.py
ppt_json-1.0.4.data/data/docs/LICENSE
ppt_json-1.0.4.data/data/docs/README
ppt_json-1.0.4.dist-info/licenses/LICENSE
ppt_json-1.0.4.dist-info/METADATA
ppt_json-1.0.4.dist-info/WHEEL
ppt_json-1.0.4.dist-info/top_level.txt
ppt_json-1.0.4.dist-info/RECORD
